.foundryrc
.gitignore
.travis.yml
CHANGELOG.rst
MANIFEST.in
README.rst
UNLICENSE
Vagrantfile
release.sh
requirements-dev.txt
requirements.txt
setup.py
test.sh
sublime_plugin_tests_base/__init__.py
sublime_plugin_tests_base/logger.py
sublime_plugin_tests_base/sublime_plugin_tests_base.py
sublime_plugin_tests_base.egg-info/PKG-INFO
sublime_plugin_tests_base.egg-info/SOURCES.txt
sublime_plugin_tests_base.egg-info/dependency_links.txt
sublime_plugin_tests_base.egg-info/pbr.json
sublime_plugin_tests_base.egg-info/requires.txt
sublime_plugin_tests_base.egg-info/top_level.txt
sublime_plugin_tests_base/templates/__init__.py
sublime_plugin_tests_base/templates/plugin.py
sublime_plugin_tests_base/utils/__init__.py
sublime_plugin_tests_base/utils/scratch_view.py
sublime_plugin_tests_base/utils/selection.py