Metadata-Version: 1.1
Name: sublime_plugin_tests_base
Version: 1.0.0
Summary: Base layer for testing and assertion frameworks against Sublime Text
Home-page: https://github.com/twolfson/sublime-plugin-tests-base
Author: Todd Wolfson
Author-email: todd@twolfson.com
License: UNLICENSE
Download-URL: https://github.com/twolfson/sublime-plugin-tests-base/archive/master.zip
Keywords: sublime,plugin,test,assert
Platform: UNKNOWN
Classifier: Development Status :: 3 - Alpha
Classifier: Intended Audience :: Developers
Classifier: License :: Public Domain
Classifier: Operating System :: OS Independent
Classifier: Programming Language :: Python
Classifier: Topic :: Software Development :: Testing
Classifier: Topic :: Text Editors
